LICENSE
hydrus_api/__init__.py
hydrus_api/utils.py
hydrus_api-5.1.1.dist-info/LICENSE
hydrus_api-5.1.1.dist-info/METADATA
hydrus_api-5.1.1.dist-info/WHEEL
hydrus_api-5.1.1.dist-info/RECORD
