Metadata-Version: 2.1
Name: hydrus-api
Version: 5.1.1
Summary: Python module implementing the Hydrus API
Home-page: https://gitlab.com/cryzed/hydrus-api
License: AGPL-3.0-or-later
Keywords: hydrus,api
Author: cryzed
Author-email: cryzed@googlemail.com
Requires-Python: >=3.9,<4.0
Classifier: License :: OSI Approved :: GNU Affero General Public License v3 or later (AGPLv3+)
Classifier: Programming Language :: Python :: 3
Classifier: Programming Language :: Python :: 3.9
Classifier: Programming Language :: Python :: 3.10
Classifier: Programming Language :: Python :: 3.11
Classifier: Programming Language :: Python :: 3.12
Requires-Dist: requests (>=2.28.2,<3.0.0)
Project-URL: Repository, https://gitlab.com/cryzed/hydrus-api
